{"title":"2020年苹果开发者大会","description":"2020 Apple Worldwide Developers Conference","keywords":"apple,2020,wwdc","labels":["随笔"],"date":"2020-06-23","path":"2020/06/apple-wwdc-2020.md","slug":"2020_06_apple-wwdc-2020","html":"<p>昨晚苹果线上直播了2020年开发者大会。本次大会给了不少的东西出来。其中最引瞩目的就是宣布自研Mac ARM芯片，从Intel中跳出来。</p>\n<p>这是苹果想统一多平台下的一个大棋。在会之前就有不少的人分析arm架构的处理器会给市场带来什么影响。用户无需考虑太多，而开发者倒会更多的考虑开发兼容性的问题。</p>\n<h2 id=\"苹果生态\">苹果生态</h2>\n<p>毫无疑问，苹果在生态上走的越来越靠拢，强化多平台优秀的体验拉拢了越来越多的用户。我个人觉得iOS很流畅，能稳定的运行不会忽然卡顿就已经很满足了。但也非常不喜欢苹果的一些缺失的功能。拿着超前的体验做着安卓好几年前就有的功能，不知道iOS开发的执行力是不是不够，但个别地方的体验真的不尽人意。短信不能未读提示，电量不足20%还强制弹窗提示...有好多地方在产品的设计上就有问题。</p>\n<p>后面接触了macOS，我常将它比作是ui更精致，系统更稳定的linux。开发体验非常好，从此告别了windows。windows在开发过程总会遇到不明不白的卡顿问题，terminal也总是让人觉得帧数很低不顺畅。还有一个很重要的优点就是macOS没有广告弹窗，这点就不得不吐槽windows下国产应用肆意妄为弹窗、捆绑了。未来会一直用macOS开发，总结一个词就是相见恨晚。</p>\n<p><img align=\"center\" style=\"width: 100%;margin-bottom: 20px;border-radius: 8px;background: #f8fdf3;\" data-zoomable src=\"https://i.loli.net/2020/06/23/Agv9hHwZI4eMyqT.jpg\" alt=\"007S8ZIlgy1gg24hxohtfj31c00u07wn.jpg\" ></p>\n<p>新的macOS ui有了更新，图标改为了圆角矩形，和ipadOS、iOS越来越相似。个人觉得改动并不会丑，大概率又会是真香体验。</p>\n"}